<form>
  <label>EventHub Audit Dashboard</label>
  <description>Audit events that are subscribing to EventHub will populate this dashboard</description>
  <fieldset submitButton="false" autoRun="false">
    <input type="time" token="time" searchWhenChanged="true">
      <label>Time</label>
      <default>
        <earliest>-7d@h</earliest>
        <latest>now</latest>
      </default>
    </input>
    <input type="dropdown" token="rgroup" searchWhenChanged="true">
      <label>Resource Group</label>
      <default>*</default>
      <initialValue>*</initialValue>
      <fieldForLabel>resource_group</fieldForLabel>
      <fieldForValue>resource_group</fieldForValue>
      <search>
        <query>`azure_eventhub_index` sourcetype="eventhub:audit*" 
| stats count by resource_group</query>
        <earliest>$time.earliest$</earliest>
        <latest>$time.latest$</latest>
      </search>
      <choice value="*">All</choice>
    </input>
    <input type="checkbox" token="show_panel" searchWhenChanged="true">
      <label>Show Field Summary</label>
      <choice value="1">Yes</choice>
      <delimiter> </delimiter>
    </input>
  </fieldset>
  <row>
    <panel id="first_panel">
      <title>Resource Groups Utilized</title>
      <chart>
        <search>
          <query>`azure_eventhub_index` sourcetype="eventhub:audit*" resource_group="$rgroup$"
| eval resource_group=UPPER(resource_group)
| stats count by resource_group</query>
          <earliest>$time.earliest$</earliest>
          <latest>$time.latest$</latest>
          <sampleRatio>1</sampleRatio>
        </search>
        <option name="charting.axisLabelsX.majorLabelStyle.overflowMode">ellipsisNone</option>
        <option name="charting.axisLabelsX.majorLabelStyle.rotation">0</option>
        <option name="charting.axisTitleX.visibility">visible</option>
        <option name="charting.axisTitleY.visibility">visible</option>
        <option name="charting.axisTitleY2.visibility">visible</option>
        <option name="charting.axisX.abbreviation">none</option>
        <option name="charting.axisX.scale">linear</option>
        <option name="charting.axisY.abbreviation">none</option>
        <option name="charting.axisY.scale">linear</option>
        <option name="charting.axisY2.abbreviation">none</option>
        <option name="charting.axisY2.enabled">0</option>
        <option name="charting.axisY2.scale">inherit</option>
        <option name="charting.chart">bar</option>
        <option name="charting.chart.bubbleMaximumSize">50</option>
        <option name="charting.chart.bubbleMinimumSize">10</option>
        <option name="charting.chart.bubbleSizeBy">area</option>
        <option name="charting.chart.nullValueMode">gaps</option>
        <option name="charting.chart.showDataLabels">none</option>
        <option name="charting.chart.sliceCollapsingThreshold">0.01</option>
        <option name="charting.chart.stackMode">default</option>
        <option name="charting.chart.style">shiny</option>
        <option name="charting.drilldown">none</option>
        <option name="charting.layout.splitSeries">0</option>
        <option name="charting.layout.splitSeries.allowIndependentYRanges">0</option>
        <option name="charting.legend.labelStyle.overflowMode">ellipsisMiddle</option>
        <option name="charting.legend.mode">standard</option>
        <option name="charting.legend.placement">right</option>
        <option name="charting.lineWidth">2</option>
        <option name="refresh.display">progressbar</option>
        <option name="trellis.enabled">0</option>
        <option name="trellis.scales.shared">1</option>
        <option name="trellis.size">medium</option>
      </chart>
    </panel>
    <panel id="second_panel">
      <chart>
        <title>Subscription Detected</title>
        <search>
          <query>`azure_eventhub_index` sourcetype="eventhub:audit*" resource_group="$rgroup$" | stats count by subscription</query>
          <earliest>$time.earliest$</earliest>
          <latest>$time.latest$</latest>
        </search>
        <option name="charting.chart">pie</option>
        <option name="charting.drilldown">none</option>
        <option name="refresh.display">progressbar</option>
      </chart>
    </panel>
    <panel id="third_panel">
      <title>Public DNSs</title>
      <table>
        <search>
          <query>`azure_eventhub_index` sourcetype="eventhub:audit*" provider_type=Public*
| stats count by provider_account
| fields provider_account 
| rename provider_account AS "DNS Configured"</query>
          <earliest>$time.earliest$</earliest>
          <latest>$time.latest$</latest>
          <sampleRatio>1</sampleRatio>
        </search>
        <option name="count">20</option>
        <option name="dataOverlayMode">none</option>
        <option name="drilldown">none</option>
        <option name="percentagesRow">false</option>
        <option name="refresh.display">progressbar</option>
        <option name="rowNumbers">false</option>
        <option name="totalsRow">false</option>
        <option name="wrap">true</option>
      </table>
    </panel>
  </row>
  <row>
    <panel depends="$alwaysHideCSS$">
      <html>
     <style>
       #first_panel{
         width:40% !important;
       }
       #second_panel{
         width:40% !important;
       }
       #third_panel{
         width:20% !important;
       }
     </style>
   </html>
    </panel>
    <panel>
      <title>Data Operation Name</title>
      <chart>
        <search>
          <query>`azure_eventhub_index` sourcetype="eventhub:audit*" resource_group="$rgroup$"
| timechart span=1h count by "{}.data.operationName" usenull=false</query>
          <earliest>$time.earliest$</earliest>
          <latest>$time.latest$</latest>
          <sampleRatio>1</sampleRatio>
        </search>
        <option name="charting.axisLabelsX.majorLabelStyle.overflowMode">ellipsisNone</option>
        <option name="charting.axisLabelsX.majorLabelStyle.rotation">0</option>
        <option name="charting.axisTitleX.visibility">visible</option>
        <option name="charting.axisTitleY.visibility">visible</option>
        <option name="charting.axisTitleY2.visibility">visible</option>
        <option name="charting.axisX.abbreviation">none</option>
        <option name="charting.axisX.scale">linear</option>
        <option name="charting.axisY.abbreviation">none</option>
        <option name="charting.axisY.scale">linear</option>
        <option name="charting.axisY2.abbreviation">none</option>
        <option name="charting.axisY2.enabled">0</option>
        <option name="charting.axisY2.scale">inherit</option>
        <option name="charting.chart">line</option>
        <option name="charting.chart.bubbleMaximumSize">50</option>
        <option name="charting.chart.bubbleMinimumSize">10</option>
        <option name="charting.chart.bubbleSizeBy">area</option>
        <option name="charting.chart.nullValueMode">gaps</option>
        <option name="charting.chart.showDataLabels">none</option>
        <option name="charting.chart.sliceCollapsingThreshold">0.01</option>
        <option name="charting.chart.stackMode">default</option>
        <option name="charting.chart.style">shiny</option>
        <option name="charting.drilldown">none</option>
        <option name="charting.layout.splitSeries">0</option>
        <option name="charting.layout.splitSeries.allowIndependentYRanges">0</option>
        <option name="charting.legend.labelStyle.overflowMode">ellipsisMiddle</option>
        <option name="charting.legend.mode">standard</option>
        <option name="charting.legend.placement">right</option>
        <option name="charting.lineWidth">2</option>
        <option name="refresh.display">progressbar</option>
        <option name="trellis.enabled">0</option>
        <option name="trellis.scales.shared">1</option>
        <option name="trellis.size">medium</option>
      </chart>
    </panel>
  </row>
  <row>
    <panel>
      <title>Azure Event Hub Authorization Actions</title>
      <chart>
        <search>
          <query>`azure_eventhub_index` sourcetype="eventhub:audit*"  resource_group="$rgroup$"
|timechart span=1h count by "{}.data.authorization.action" usenull=false</query>
          <earliest>$time.earliest$</earliest>
          <latest>$time.latest$</latest>
          <sampleRatio>1</sampleRatio>
        </search>
        <option name="charting.axisLabelsX.majorLabelStyle.overflowMode">ellipsisNone</option>
        <option name="charting.axisLabelsX.majorLabelStyle.rotation">0</option>
        <option name="charting.axisTitleX.visibility">visible</option>
        <option name="charting.axisTitleY.visibility">visible</option>
        <option name="charting.axisTitleY2.visibility">visible</option>
        <option name="charting.axisX.abbreviation">none</option>
        <option name="charting.axisX.scale">linear</option>
        <option name="charting.axisY.abbreviation">none</option>
        <option name="charting.axisY.scale">linear</option>
        <option name="charting.axisY2.abbreviation">none</option>
        <option name="charting.axisY2.enabled">0</option>
        <option name="charting.axisY2.scale">inherit</option>
        <option name="charting.chart">line</option>
        <option name="charting.chart.bubbleMaximumSize">50</option>
        <option name="charting.chart.bubbleMinimumSize">10</option>
        <option name="charting.chart.bubbleSizeBy">area</option>
        <option name="charting.chart.nullValueMode">gaps</option>
        <option name="charting.chart.showDataLabels">none</option>
        <option name="charting.chart.sliceCollapsingThreshold">0.01</option>
        <option name="charting.chart.stackMode">default</option>
        <option name="charting.chart.style">shiny</option>
        <option name="charting.drilldown">none</option>
        <option name="charting.layout.splitSeries">0</option>
        <option name="charting.layout.splitSeries.allowIndependentYRanges">0</option>
        <option name="charting.legend.labelStyle.overflowMode">ellipsisMiddle</option>
        <option name="charting.legend.mode">standard</option>
        <option name="charting.legend.placement">right</option>
        <option name="charting.lineWidth">2</option>
        <option name="refresh.display">progressbar</option>
        <option name="trellis.enabled">0</option>
        <option name="trellis.scales.shared">1</option>
        <option name="trellis.size">medium</option>
      </chart>
    </panel>
    <panel>
      <title>Authorization Against Roles</title>
      <table>
        <search>
          <query>`azure_eventhub_index` sourcetype="eventhub:audit*" resource_group="$rgroup$"
| stats count by "{}.data.authorization.action" "{}.data.authorization.evidence.role"
| rename {}.* AS *</query>
          <earliest>$time.earliest$</earliest>
          <latest>$time.latest$</latest>
          <sampleRatio>1</sampleRatio>
        </search>
        <option name="count">20</option>
        <option name="dataOverlayMode">none</option>
        <option name="drilldown">none</option>
        <option name="percentagesRow">false</option>
        <option name="refresh.display">progressbar</option>
        <option name="rowNumbers">false</option>
        <option name="totalsRow">false</option>
        <option name="wrap">true</option>
      </table>
    </panel>
  </row>
  <row>
    <panel>
      <title>Data Operation Status</title>
      <table>
        <search>
          <query>`azure_eventhub_index` sourcetype="eventhub:audit*" resource_group="$rgroup$"
| stats count by "{}.data.resourceProvider" "{}.data.operationName" "{}.data.authorization.action" "{}.data.status" 
| rename {}.* as *</query>
          <earliest>$time.earliest$</earliest>
          <latest>$time.latest$</latest>
          <sampleRatio>1</sampleRatio>
        </search>
        <option name="count">20</option>
        <option name="dataOverlayMode">none</option>
        <option name="drilldown">cell</option>
        <option name="percentagesRow">false</option>
        <option name="refresh.display">progressbar</option>
        <option name="rowNumbers">false</option>
        <option name="totalsRow">false</option>
        <option name="wrap">true</option>
        <drilldown>
          <link target="_blank">search?q=index=eventhub sourcetype="eventhub:audit:log" resource_group="cloud-shell-storage-eastus"
| rename {}.* as *
| search "data.resourceProvider"="$click.value$"&amp;earliest=$time.earliest$&amp;latest=$time.latest$</link>
        </drilldown>
      </table>
    </panel>
  </row>
  <row>
    <panel>
      <table>
        <title>Provider Types and Accounts Created</title>
        <search>
          <query>`azure_eventhub_index` sourcetype="eventhub:audit*"
| stats count by provider_type provider_account
| fields provider_type provider_account</query>
          <earliest>$time.earliest$</earliest>
          <latest>$time.latest$</latest>
        </search>
        <option name="drilldown">cell</option>
        <option name="refresh.display">progressbar</option>
        <drilldown>
          <link target="_blank">search?q=index=eventhub sourcetype="eventhub:audit:log"
| rename {}.* as *
| search provider_type="$click.value$" *$click.value2$*&amp;earliest=$time.earliest$&amp;latest=$time.latest$</link>
        </drilldown>
      </table>
    </panel>
  </row>
  <row>
    <panel depends="$show_panel$">
      <title>Field Summary</title>
      <table>
        <search>
          <query>`azure_eventhub_index` sourcetype="eventhub:audit*" resource_group="$rgroup$"
| fieldsummary maxvals=5 
| search field=*{*
| fields field count is_exact max mean min values</query>
          <earliest>$time.earliest$</earliest>
          <latest>$time.latest$</latest>
          <sampleRatio>1</sampleRatio>
        </search>
        <option name="count">10</option>
        <option name="dataOverlayMode">none</option>
        <option name="drilldown">none</option>
        <option name="percentagesRow">false</option>
        <option name="refresh.display">progressbar</option>
        <option name="rowNumbers">false</option>
        <option name="totalsRow">false</option>
        <option name="wrap">true</option>
      </table>
    </panel>
  </row>
</form>